etcd_client/__init__.py
etcd_client/etcd_client.cpython-314t-x86_64-linux-gnu.so
etcd_client_py-0.5.1.dist-info/METADATA
etcd_client_py-0.5.1.dist-info/WHEEL
etcd_client_py-0.5.1.dist-info/licenses/LICENSE
etcd_client_py-0.5.1.dist-info/RECORD
