Metadata-Version: 2.4
Name: etcd-client-py
Version: 0.5.1
Classifier: Development Status :: 4 - Beta
Classifier: Programming Language :: Python
Classifier: Programming Language :: Python :: 3.10
Classifier: Programming Language :: Python :: 3.11
Classifier: Programming Language :: Python :: 3.12
Classifier: Programming Language :: Python :: 3.13
Classifier: Programming Language :: Python :: 3.14
Requires-Dist: maturin>=1.11,<2.0 ; extra == 'dev'
Requires-Dist: ruff>=0.14.10 ; extra == 'dev'
Requires-Dist: mypy>=1.19.1 ; extra == 'dev'
Requires-Dist: pytest>=9.0.2,<10 ; extra == 'test'
Requires-Dist: pytest-asyncio>=1.3.0,<2 ; extra == 'test'
Requires-Dist: trafaret>=2.1,<3 ; extra == 'test'
Requires-Dist: testcontainers>=4.13.3,<5 ; extra == 'test'
Provides-Extra: dev
Provides-Extra: test
License-File: LICENSE
Summary: Yet another etcd-client API binding based on the Rust's etcd-client package
Keywords: etcd,binding,rust,etcd-client
Author: Sanghyeon Seo, Joongi Kim
Author-email: seosh@lablup.com, joongi@lablup.com
License-Expression: MIT
Requires-Python: >=3.10
Project-URL: homepage, https://github.com/lablup/etcd-client-py
Project-URL: repository, https://github.com/lablup/etcd-client-py
